CHANGELOG.md
LICENSE
MANIFEST.in
README.md
requirements.txt
setup.py
threebot_worker/__init__.py
threebot_worker/daemon.py
threebot_worker/threebot-worker
threebot_worker.egg-info/PKG-INFO
threebot_worker.egg-info/SOURCES.txt
threebot_worker.egg-info/dependency_links.txt
threebot_worker.egg-info/requires.txt
threebot_worker.egg-info/top_level.txt