Metadata-Version: 1.0
Name: threebot-worker
Version: 0.1.3
Summary: Worker scripts for the 3bot plattform
Home-page: https://github.com/3bot/3bot-worker
Author: arteria GmbH
Author-email: renner@arteria.ch
License: UNKNOWN
Platform: UNKNOWN
